dafd/__init__.py
dafd/bin/DAFD_Interface.py
dafd/bin/ForwardModelTester.py
dafd/cmd_inputs.txt
dafd/core_logic/ForwardModel.py
dafd/core_logic/InterModel.py
dafd/core_logic/RegimeClassifier.py
dafd/core_logic/Regressor.py
dafd/helper_scripts/DAFD_logo.png
dafd/helper_scripts/ModelHelper.py
dafd/helper_scripts/experimental_data/ExperimentalResults_5Hz.csv
dafd/helper_scripts/experimental_data/ExperimentalResults_880.csv
dafd/helper_scripts/experimental_data/ExperimentalResults_888.csv
dafd/helper_scripts/experimental_data/ExperimentalResults_990.csv
dafd/helper_scripts/experimental_data/ExperimentalResults_998.csv
dafd/model_data/VisualizeAlgorithm.py
dafd/model_data/disp_graphs.py
dafd/model_data/process_results.py
dafd/model_data/visualize_GradDesc2D.py
dafd/model_data/visualize_GradDescCharts.py
dafd/model_data/visualize_SliderAnim.py
dafd/model_data/visualize_SliderStill.py
dafd/models/forward_models/NeuralNetModel_rate1.py
dafd/models/forward_models/NeuralNetModel_rate2.py
dafd/models/forward_models/NeuralNetModel_size1.py
dafd/models/forward_models/NeuralNetModel_size2.py
dafd/models/forward_models/saved/README.md
dafd/models/forward_models/saved/droplet_size1.h5
dafd/models/forward_models/saved/droplet_size1.json
dafd/models/forward_models/saved/droplet_size2.h5
dafd/models/forward_models/saved/droplet_size2.json
dafd/models/forward_models/saved/generation_rate1.h5
dafd/models/forward_models/saved/generation_rate1.json
dafd/models/forward_models/saved/generation_rate2.h5
dafd/models/forward_models/saved/generation_rate2.json
dafd/models/regime_models/NeuralNetModel_regime.py
dafd/models/regime_models/saved/README.md
dafd/models/regime_models/saved/classifier.h5
dafd/models/regime_models/saved/classifier.json
dafd-0.1.1.dist-info/WHEEL
dafd-0.1.1.dist-info/METADATA
dafd-0.1.1.dist-info/RECORD
